LICENSE
README.md
lyyprocess.py
setup.py
lyyprocess.egg-info/PKG-INFO
lyyprocess.egg-info/SOURCES.txt
lyyprocess.egg-info/dependency_links.txt
lyyprocess.egg-info/requires.txt
lyyprocess.egg-info/top_level.txt