Metadata-Version: 2.1
Name: lyyprocess
Version: 0.7
Summary: lyy process tools for lyy
Author: lyy
Author-email: 
License: MIT
License-File: LICENSE
Requires-Dist: psutil
